{
  "users": [
    {
      "id": 1,
      "name": "Ayushmaan",
      "avatar": "https://encrypted-tbn0.gstatic.com/images?q=tbn:ANd9GcS2gzqD9puDYlRGb0EoHEQ-oMrOjgIXQM0hig&usqp=CAU",
      "email": "gtatterton0@ehow.com",
      "password": "1234"
    },
    {
      "id": 2,
      "name": "Raju",
      "avatar": "https://encrypted-tbn0.gstatic.com/images?q=tbn:ANd9GcS2gzqD9puDYlRGb0EoHEQ-oMrOjgIXQM0hig&usqp=CAU",
      "email": "gtatterton0@ehow.com",
      "password": "1234"
    }
  ],
  "forum": [
    {
      "questionid": 1,
      "name": "Ayushmaan",
      "title": "Javascript",
      "description": "Im learning javascript...",
      "language": "Javascript",
      "postdate": "2023-11-30",
      "upvote": 1,
      "answer": []
    }
  ]
}